setup.py
jeffrain.egg-info/PKG-INFO
jeffrain.egg-info/SOURCES.txt
jeffrain.egg-info/dependency_links.txt
jeffrain.egg-info/top_level.txt
tool/__init__.py
tool/db_tool/MongoQue.py
tool/db_tool/__init__.py
tool/mail_tool/__init__.py
tool/mail_tool/mailUtil.py
tool/spider_tool/__init__.py
tool/spider_tool/cookieUtil.py
tool/str_tool/__init__.py
tool/str_tool/strUtil.py
tool/time_tool/__init__.py
tool/time_tool/timeUtil.py