Metadata-Version: 1.0
Name: jeffrain
Version: 1.1
Summary: just a tool set
Home-page: UNKNOWN
Author: J
Author-email: z.798818344@163.com
License: UNKNOWN
Platform: any
